jno/__init__.py
jno/__main__.py
jno/util.py
jno/commands/__init__.py
jno/commands/boards.py
jno/commands/build.py
jno/commands/clean.py
jno/commands/command.py
jno/commands/init.py
jno/commands/jnohelp.py
jno/commands/jnoserial.py
jno/commands/ports.py
jno/commands/setdefault.py
jno/commands/upload.py
jno-0.5.0.dist-info/LICENSE.txt
jno-0.5.0.dist-info/METADATA
jno-0.5.0.dist-info/WHEEL
jno-0.5.0.dist-info/entry_points.txt
jno-0.5.0.dist-info/top_level.txt
jno-0.5.0.dist-info/RECORD
