Metadata-Version: 2.1
Name: jno
Version: 0.5.0
Summary: Command line interface wrapper for Arduino IDE, inspired by ino
Home-page: https://github.com/kosinkadink/jno
Author: Jedrzej Kosinski
Author-email: kosinkadink1@gmail.com
License: MIT
Keywords: arduino interface ide wrapper
Platform: UNKNOWN
Classifier: Development Status :: 4 - Beta
Classifier: License :: OSI Approved :: MIT License
Classifier: Intended Audience :: Developers
Classifier: Operating System :: OS Independent
Classifier: Programming Language :: Python :: 2
Classifier: Programming Language :: Python :: 3
Classifier: Topic :: Software Development :: Embedded Systems
Requires-Dist: pyserial
Requires-Dist: colorama
